.coveragerc
.travis.yml
CHANGES.txt
LICENSE
MANIFEST.in
README.rst
pytest.ini
setup.cfg
setup.py
tox.ini
pyramlson/__init__.py
pyramlson/apidef.py
pyramlson/error.py
pyramlson/utils.py
pyramlson.egg-info/PKG-INFO
pyramlson.egg-info/SOURCES.txt
pyramlson.egg-info/dependency_links.txt
pyramlson.egg-info/not-zip-safe
pyramlson.egg-info/requires.txt
pyramlson.egg-info/top_level.txt
tests/__init__.py
tests/bad_resource.py
tests/base.py
tests/error_resource.py
tests/resource.py
tests/test_apidef.py
tests/test_errors.py
tests/test_resource.py
tests/data/test-api.raml
tests/data/test-errors-api.raml
tests/data/schemas/BookRecord.json
tests/data/schemas/BookRecordList.json
tests/data/schemas/credentials.json
tests/data/schemas/token.json