Metadata-Version: 1.1
Name: pyramlson
Version: 1.3.1
Summary: pyramlson
Home-page: https://github.com/ScanPlusGmbH/pyramlson
Author: ScanPlus GmbH
Author-email: devops@scanplus.de
License: UNKNOWN
Keywords: web pyramid api json
Platform: UNKNOWN
Classifier: Programming Language :: Python
Classifier: Framework :: Pyramid
Classifier: Programming Language :: Python :: 2.7
Classifier: Programming Language :: Python :: 3.4
Classifier: Programming Language :: Python :: 3.5
Classifier: Programming Language :: Python :: 3.6
Classifier: Programming Language :: Python :: Implementation :: CPython
Classifier: Programming Language :: Python :: Implementation :: PyPy
